MANIFEST.in
README.md
setup.cfg
setup.py
DamPy.egg-info/PKG-INFO
DamPy.egg-info/SOURCES.txt
DamPy.egg-info/dependency_links.txt
DamPy.egg-info/requires.txt
DamPy.egg-info/top_level.txt
dampy/__init__.py
dampy/config/config.json
dampy/lib/AEM.py
dampy/lib/Assets.py
dampy/lib/Config.py
dampy/lib/Connector.py
dampy/lib/Env.py
dampy/lib/Response.py
dampy/lib/Util.py