Metadata-Version: 2.1
Name: DamPy
Version: 0.12.4
Summary: A python tool to easily work with Adobe Experience Manager (AEM) DAM. 
Home-page: https://github.com/ashokkumarta/dampy
Author: Ashokkumar T.A
Author-email: ashokkumar.ta@gmail.com
License: MIT
Keywords: AEM,DAM,Python tool,list,create,upload,download,activate,deactivate,delete
Platform: UNKNOWN
Classifier: Development Status :: 3 - Alpha
Classifier: Intended Audience :: Developers
Classifier: Topic :: Software Development :: Build Tools
Classifier: License :: OSI Approved :: MIT License
Classifier: Programming Language :: Python :: 3.4
Classifier: Programming Language :: Python :: 3.5
Classifier: Programming Language :: Python :: 3.6
Classifier: Programming Language :: Python :: 3.7
